cache/__init__.py
cache/apps.py
cache/middleware.py
cache/settings.py
django_requests_cache-0.1.11.dist-info/METADATA
django_requests_cache-0.1.11.dist-info/RECORD
django_requests_cache-0.1.11.dist-info/WHEEL
django_requests_cache-0.1.11.dist-info/top_level.txt
